[
  {
    "inputs": [],
    "name": "AccessControlBadConfirmation",
    "type": "error"
  },
  {
    "inputs": [
      {
        "internalType": "address",
        "name": "account",
        "type": "address"
      },
      {
        "internalType": "bytes32",
        "name": "neededRole",
        "type": "bytes32"
      }
    ],
    "name": "AccessControlUnauthorizedAccount",
    "type": "error"
  },
  {
    "inputs": [],
    "name": "InvalidInitialization",
    "type": "error"
  },
  {
    "inputs": [],
    "name": "NotInitializing",
    "type": "error"
  },
  {
    "inputs": [],
    "name": "ReentrancyGuardReentrantCall",
    "type": "error"
  },
  {
    "anonymous": false,
    "inputs": [
      {
        "indexed": true,
        "internalType": "enum ThreeGatesRiskManager.GateType",
        "name": "gateType",
        "type": "uint8"
      },
      {
        "indexed": true,
        "internalType": "address",
        "name": "user",
        "type": "address"
      },
      {
        "indexed": true,
        "internalType": "bytes32",
        "name": "market",
        "type": "bytes32"
      },
      {
        "indexed": false,
        "internalType": "uint256",
        "name": "threshold",
        "type": "uint256"
      },
      {
        "indexed": false,
        "internalType": "uint256",
        "name": "timestamp",
        "type": "uint256"
      }
    ],
    "name": "CircuitBreakerTriggered",
    "type": "event"
  },
  {
    "anonymous": false,
    "inputs": [
      {
        "indexed": true,
        "internalType": "address",
        "name": "user",
        "type": "address"
      },
      {
        "indexed": false,
        "internalType": "uint256",
        "name": "oldFactor",
        "type": "uint256"
      },
      {
        "indexed": false,
        "internalType": "uint256",
        "name": "newFactor",
        "type": "uint256"
      },
      {
        "indexed": false,
        "internalType": "string",
        "name": "reason",
        "type": "string"
      },
      {
        "indexed": false,
        "internalType": "uint256",
        "name": "timestamp",
        "type": "uint256"
      }
    ],
    "name": "DynamicAdjustmentApplied",
    "type": "event"
  },
  {
    "anonymous": false,
    "inputs": [
      {
        "indexed": false,
        "internalType": "bool",
        "name": "enabled",
        "type": "bool"
      },
      {
        "indexed": true,
        "internalType": "address",
        "name": "admin",
        "type": "address"
      },
      {
        "indexed": false,
        "internalType": "string",
        "name": "reason",
        "type": "string"
      },
      {
        "indexed": false,
        "internalType": "uint256",
        "name": "timestamp",
        "type": "uint256"
      }
    ],
    "name": "EmergencyModeToggled",
    "type": "event"
  },
  {
    "anonymous": false,
    "inputs": [
      {
        "indexed": false,
        "internalType": "uint64",
        "name": "version",
        "type": "uint64"
      }
    ],
    "name": "Initialized",
    "type": "event"
  },
  {
    "anonymous": false,
    "inputs": [
      {
        "indexed": true,
        "internalType": "address",
        "name": "user",
        "type": "address"
      },
      {
        "indexed": true,
        "internalType": "bytes32",
        "name": "market",
        "type": "bytes32"
      },
      {
        "indexed": false,
        "internalType": "enum ThreeGatesRiskManager.GateType",
        "name": "gateType",
        "type": "uint8"
      },
      {
        "indexed": false,
        "internalType": "uint256",
        "name": "attemptedAmount",
        "type": "uint256"
      },
      {
        "indexed": false,
        "internalType": "uint256",
        "name": "currentLimit",
        "type": "uint256"
      },
      {
        "indexed": false,
        "internalType": "uint256",
        "name": "timestamp",
        "type": "uint256"
      }
    ],
    "name": "RiskGateTriggered",
    "type": "event"
  },
  {
    "anonymous": false,
    "inputs": [
      {
        "indexed": true,
        "internalType": "address",
        "name": "user",
        "type": "address"
      },
      {
        "indexed": false,
        "internalType": "enum ThreeGatesRiskManager.GateType",
        "name": "gateType",
        "type": "uint8"
      },
      {
        "indexed": false,
        "internalType": "uint256",
        "name": "oldLimit",
        "type": "uint256"
      },
      {
        "indexed": false,
        "internalType": "uint256",
        "name": "newLimit",
        "type": "uint256"
      },
      {
        "indexed": false,
        "internalType": "uint256",
        "name": "timestamp",
        "type": "uint256"
      }
    ],
    "name": "RiskLimitsUpdated",
    "type": "event"
  },
  {
    "anonymous": false,
    "inputs": [
      {
        "indexed": true,
        "internalType": "bytes32",
        "name": "eventId",
        "type": "bytes32"
      },
      {
        "indexed": true,
        "internalType": "address",
        "name": "user",
        "type": "address"
      },
      {
        "indexed": true,
        "internalType": "bytes32",
        "name": "market",
        "type": "bytes32"
      },
      {
        "indexed": false,
        "internalType": "enum ThreeGatesRiskManager.GateType",
        "name": "gateType",
        "type": "uint8"
      },
      {
        "indexed": false,
        "internalType": "uint256",
        "name": "severity",
        "type": "uint256"
      }
    ],
    "name": "RiskViolation",
    "type": "event"
  },
  {
    "anonymous": false,
    "inputs": [
      {
        "indexed": true,
        "internalType": "bytes32",
        "name": "role",
        "type": "bytes32"
      },
      {
        "indexed": true,
        "internalType": "bytes32",
        "name": "previousAdminRole",
        "type": "bytes32"
      },
      {
        "indexed": true,
        "internalType": "bytes32",
        "name": "newAdminRole",
        "type": "bytes32"
      }
    ],
    "name": "RoleAdminChanged",
    "type": "event"
  },
  {
    "anonymous": false,
    "inputs": [
      {
        "indexed": true,
        "internalType": "bytes32",
        "name": "role",
        "type": "bytes32"
      },
      {
        "indexed": true,
        "internalType": "address",
        "name": "account",
        "type": "address"
      },
      {
        "indexed": true,
        "internalType": "address",
        "name": "sender",
        "type": "address"
      }
    ],
    "name": "RoleGranted",
    "type": "event"
  },
  {
    "anonymous": false,
    "inputs": [
      {
        "indexed": true,
        "internalType": "bytes32",
        "name": "role",
        "type": "bytes32"
      },
      {
        "indexed": true,
        "internalType": "address",
        "name": "account",
        "type": "address"
      },
      {
        "indexed": true,
        "internalType": "address",
        "name": "sender",
        "type": "address"
      }
    ],
    "name": "RoleRevoked",
    "type": "event"
  },
  {
    "inputs": [],
    "name": "ADMIN_ROLE",
    "outputs": [
      {
        "internalType": "bytes32",
        "name": "",
        "type": "bytes32"
      }
    ],
    "stateMutability": "view",
    "type": "function"
  },
  {
    "inputs": [],
    "name": "CIRCUIT_BREAKER_ROLE",
    "outputs": [
      {
        "internalType": "bytes32",
        "name": "",
        "type": "bytes32"
      }
    ],
    "stateMutability": "view",
    "type": "function"
  },
  {
    "inputs": [],
    "name": "DEFAULT_ADMIN_ROLE",
    "outputs": [
      {
        "internalType": "bytes32",
        "name": "",
        "type": "bytes32"
      }
    ],
    "stateMutability": "view",
    "type": "function"
  },
  {
    "inputs": [],
    "name": "RISK_OPERATOR_ROLE",
    "outputs": [
      {
        "internalType": "bytes32",
        "name": "",
        "type": "bytes32"
      }
    ],
    "stateMutability": "view",
    "type": "function"
  },
  {
    "inputs": [
      {
        "internalType": "uint256",
        "name": "",
        "type": "uint256"
      }
    ],
    "name": "allMarkets",
    "outputs": [
      {
        "internalType": "bytes32",
        "name": "",
        "type": "bytes32"
      }
    ],
    "stateMutability": "view",
    "type": "function"
  },
  {
    "inputs": [
      {
        "internalType": "uint256",
        "name": "",
        "type": "uint256"
      }
    ],
    "name": "allRiskEvents",
    "outputs": [
      {
        "internalType": "bytes32",
        "name": "",
        "type": "bytes32"
      }
    ],
    "stateMutability": "view",
    "type": "function"
  },
  {
    "inputs": [
      {
        "internalType": "uint256",
        "name": "",
        "type": "uint256"
      }
    ],
    "name": "allUsers",
    "outputs": [
      {
        "internalType": "address",
        "name": "",
        "type": "address"
      }
    ],
    "stateMutability": "view",
    "type": "function"
  },
  {
    "inputs": [
      {
        "internalType": "address",
        "name": "user",
        "type": "address"
      },
      {
        "internalType": "bytes32",
        "name": "market",
        "type": "bytes32"
      },
      {
        "internalType": "uint256",
        "name": "tradeSize",
        "type": "uint256"
      },
      {
        "internalType": "uint256",
        "name": "leverage",
        "type": "uint256"
      }
    ],
    "name": "checkThreeGates",
    "outputs": [
      {
        "internalType": "bool",
        "name": "allowed",
        "type": "bool"
      },
      {
        "internalType": "enum ThreeGatesRiskManager.GateType",
        "name": "blockedGate",
        "type": "uint8"
      }
    ],
    "stateMutability": "nonpayable",
    "type": "function"
  },
  {
    "inputs": [
      {
        "internalType": "enum ThreeGatesRiskManager.GateType",
        "name": "",
        "type": "uint8"
      }
    ],
    "name": "circuitBreakers",
    "outputs": [
      {
        "internalType": "uint256",
        "name": "threshold",
        "type": "uint256"
      },
      {
        "internalType": "uint256",
        "name": "duration",
        "type": "uint256"
      },
      {
        "internalType": "uint256",
        "name": "cooldownPeriod",
        "type": "uint256"
      },
      {
        "internalType": "uint256",
        "name": "lastTriggered",
        "type": "uint256"
      },
      {
        "internalType": "bool",
        "name": "isTriggered",
        "type": "bool"
      },
      {
        "internalType": "bool",
        "name": "isActive",
        "type": "bool"
      },
      {
        "internalType": "uint256",
        "name": "triggerCount",
        "type": "uint256"
      }
    ],
    "stateMutability": "view",
    "type": "function"
  },
  {
    "inputs": [
      {
        "internalType": "bytes32",
        "name": "market",
        "type": "bytes32"
      },
      {
        "internalType": "uint256",
        "name": "singleWindowLimit",
        "type": "uint256"
      },
      {
        "internalType": "uint256",
        "name": "fifteenMinuteLimit",
        "type": "uint256"
      },
      {
        "internalType": "uint256",
        "name": "twentyFourHourLimit",
        "type": "uint256"
      },
      {
        "internalType": "uint256",
        "name": "maxLeverage",
        "type": "uint256"
      }
    ],
    "name": "configureMarketRisk",
    "outputs": [],
    "stateMutability": "nonpayable",
    "type": "function"
  },
  {
    "inputs": [
      {
        "internalType": "enum ThreeGatesRiskManager.GateType",
        "name": "",
        "type": "uint8"
      }
    ],
    "name": "gateViolations",
    "outputs": [
      {
        "internalType": "uint256",
        "name": "",
        "type": "uint256"
      }
    ],
    "stateMutability": "view",
    "type": "function"
  },
  {
    "inputs": [],
    "name": "getAllRiskEvents",
    "outputs": [
      {
        "internalType": "bytes32[]",
        "name": "eventIds",
        "type": "bytes32[]"
      }
    ],
    "stateMutability": "view",
    "type": "function"
  },
  {
    "inputs": [],
    "name": "getGlobalRiskMetrics",
    "outputs": [
      {
        "internalType": "uint256",
        "name": "riskScore",
        "type": "uint256"
      },
      {
        "internalType": "uint256",
        "name": "leverageRatio",
        "type": "uint256"
      },
      {
        "internalType": "uint256",
        "name": "totalExposure",
        "type": "uint256"
      },
      {
        "internalType": "bool",
        "name": "emergencyMode",
        "type": "bool"
      }
    ],
    "stateMutability": "view",
    "type": "function"
  },
  {
    "inputs": [
      {
        "internalType": "bytes32",
        "name": "market",
        "type": "bytes32"
      }
    ],
    "name": "getMarketRiskConfig",
    "outputs": [
      {
        "components": [
          {
            "components": [
              {
                "internalType": "uint256",
                "name": "limit",
                "type": "uint256"
              },
              {
                "internalType": "uint256",
                "name": "currentUsage",
                "type": "uint256"
              },
              {
                "internalType": "uint256",
                "name": "lastResetTime",
                "type": "uint256"
              },
              {
                "internalType": "uint256",
                "name": "resetInterval",
                "type": "uint256"
              },
              {
                "internalType": "bool",
                "name": "isActive",
                "type": "bool"
              },
              {
                "internalType": "uint256",
                "name": "utilizationRate",
                "type": "uint256"
              }
            ],
            "internalType": "struct ThreeGatesRiskManager.RiskGate",
            "name": "singleWindow",
            "type": "tuple"
          },
          {
            "components": [
              {
                "internalType": "uint256",
                "name": "limit",
                "type": "uint256"
              },
              {
                "internalType": "uint256",
                "name": "currentUsage",
                "type": "uint256"
              },
              {
                "internalType": "uint256",
                "name": "lastResetTime",
                "type": "uint256"
              },
              {
                "internalType": "uint256",
                "name": "resetInterval",
                "type": "uint256"
              },
              {
                "internalType": "bool",
                "name": "isActive",
                "type": "bool"
              },
              {
                "internalType": "uint256",
                "name": "utilizationRate",
                "type": "uint256"
              }
            ],
            "internalType": "struct ThreeGatesRiskManager.RiskGate",
            "name": "fifteenMinute",
            "type": "tuple"
          },
          {
            "components": [
              {
                "internalType": "uint256",
                "name": "limit",
                "type": "uint256"
              },
              {
                "internalType": "uint256",
                "name": "currentUsage",
                "type": "uint256"
              },
              {
                "internalType": "uint256",
                "name": "lastResetTime",
                "type": "uint256"
              },
              {
                "internalType": "uint256",
                "name": "resetInterval",
                "type": "uint256"
              },
              {
                "internalType": "bool",
                "name": "isActive",
                "type": "bool"
              },
              {
                "internalType": "uint256",
                "name": "utilizationRate",
                "type": "uint256"
              }
            ],
            "internalType": "struct ThreeGatesRiskManager.RiskGate",
            "name": "twentyFourHour",
            "type": "tuple"
          },
          {
            "internalType": "uint256",
            "name": "volatilityScore",
            "type": "uint256"
          },
          {
            "internalType": "uint256",
            "name": "liquidityScore",
            "type": "uint256"
          },
          {
            "internalType": "uint256",
            "name": "openInterest",
            "type": "uint256"
          },
          {
            "internalType": "uint256",
            "name": "dailyVolume",
            "type": "uint256"
          },
          {
            "internalType": "uint256",
            "name": "maxLeverage",
            "type": "uint256"
          },
          {
            "internalType": "uint256",
            "name": "marginRequirement",
            "type": "uint256"
          },
          {
            "internalType": "uint256",
            "name": "liquidationBuffer",
            "type": "uint256"
          },
          {
            "internalType": "bool",
            "name": "isActive",
            "type": "bool"
          },
          {
            "internalType": "bool",
            "name": "emergencyMode",
            "type": "bool"
          }
        ],
        "internalType": "struct ThreeGatesRiskManager.MarketRiskConfig",
        "name": "config",
        "type": "tuple"
      }
    ],
    "stateMutability": "view",
    "type": "function"
  },
  {
    "inputs": [
      {
        "internalType": "bytes32",
        "name": "eventId",
        "type": "bytes32"
      }
    ],
    "name": "getRiskEvent",
    "outputs": [
      {
        "components": [
          {
            "internalType": "bytes32",
            "name": "eventId",
            "type": "bytes32"
          },
          {
            "internalType": "address",
            "name": "user",
            "type": "address"
          },
          {
            "internalType": "bytes32",
            "name": "market",
            "type": "bytes32"
          },
          {
            "internalType": "enum ThreeGatesRiskManager.GateType",
            "name": "gateType",
            "type": "uint8"
          },
          {
            "internalType": "uint256",
            "name": "attemptedAmount",
            "type": "uint256"
          },
          {
            "internalType": "uint256",
            "name": "currentLimit",
            "type": "uint256"
          },
          {
            "internalType": "uint256",
            "name": "timestamp",
            "type": "uint256"
          },
          {
            "internalType": "bool",
            "name": "isViolation",
            "type": "bool"
          },
          {
            "internalType": "string",
            "name": "description",
            "type": "string"
          }
        ],
        "internalType": "struct ThreeGatesRiskManager.RiskEvent",
        "name": "riskEvent",
        "type": "tuple"
      }
    ],
    "stateMutability": "view",
    "type": "function"
  },
  {
    "inputs": [
      {
        "internalType": "bytes32",
        "name": "role",
        "type": "bytes32"
      }
    ],
    "name": "getRoleAdmin",
    "outputs": [
      {
        "internalType": "bytes32",
        "name": "",
        "type": "bytes32"
      }
    ],
    "stateMutability": "view",
    "type": "function"
  },
  {
    "inputs": [
      {
        "internalType": "address",
        "name": "user",
        "type": "address"
      }
    ],
    "name": "getUserRiskProfile",
    "outputs": [
      {
        "components": [
          {
            "components": [
              {
                "internalType": "uint256",
                "name": "limit",
                "type": "uint256"
              },
              {
                "internalType": "uint256",
                "name": "currentUsage",
                "type": "uint256"
              },
              {
                "internalType": "uint256",
                "name": "lastResetTime",
                "type": "uint256"
              },
              {
                "internalType": "uint256",
                "name": "resetInterval",
                "type": "uint256"
              },
              {
                "internalType": "bool",
                "name": "isActive",
                "type": "bool"
              },
              {
                "internalType": "uint256",
                "name": "utilizationRate",
                "type": "uint256"
              }
            ],
            "internalType": "struct ThreeGatesRiskManager.RiskGate",
            "name": "singleWindow",
            "type": "tuple"
          },
          {
            "components": [
              {
                "internalType": "uint256",
                "name": "limit",
                "type": "uint256"
              },
              {
                "internalType": "uint256",
                "name": "currentUsage",
                "type": "uint256"
              },
              {
                "internalType": "uint256",
                "name": "lastResetTime",
                "type": "uint256"
              },
              {
                "internalType": "uint256",
                "name": "resetInterval",
                "type": "uint256"
              },
              {
                "internalType": "bool",
                "name": "isActive",
                "type": "bool"
              },
              {
                "internalType": "uint256",
                "name": "utilizationRate",
                "type": "uint256"
              }
            ],
            "internalType": "struct ThreeGatesRiskManager.RiskGate",
            "name": "fifteenMinute",
            "type": "tuple"
          },
          {
            "components": [
              {
                "internalType": "uint256",
                "name": "limit",
                "type": "uint256"
              },
              {
                "internalType": "uint256",
                "name": "currentUsage",
                "type": "uint256"
              },
              {
                "internalType": "uint256",
                "name": "lastResetTime",
                "type": "uint256"
              },
              {
                "internalType": "uint256",
                "name": "resetInterval",
                "type": "uint256"
              },
              {
                "internalType": "bool",
                "name": "isActive",
                "type": "bool"
              },
              {
                "internalType": "uint256",
                "name": "utilizationRate",
                "type": "uint256"
              }
            ],
            "internalType": "struct ThreeGatesRiskManager.RiskGate",
            "name": "twentyFourHour",
            "type": "tuple"
          },
          {
            "internalType": "uint256",
            "name": "riskScore",
            "type": "uint256"
          },
          {
            "internalType": "enum ThreeGatesRiskManager.RiskLevel",
            "name": "riskLevel",
            "type": "uint8"
          },
          {
            "internalType": "uint256",
            "name": "totalExposure",
            "type": "uint256"
          },
          {
            "internalType": "uint256",
            "name": "leverageRatio",
            "type": "uint256"
          },
          {
            "internalType": "uint256",
            "name": "violationCount",
            "type": "uint256"
          },
          {
            "internalType": "uint256",
            "name": "lastViolationTime",
            "type": "uint256"
          },
          {
            "internalType": "uint256",
            "name": "averageTradeSize",
            "type": "uint256"
          },
          {
            "internalType": "uint256",
            "name": "tradingFrequency",
            "type": "uint256"
          },
          {
            "internalType": "bool",
            "name": "dynamicLimitsEnabled",
            "type": "bool"
          },
          {
            "internalType": "uint256",
            "name": "adjustmentFactor",
            "type": "uint256"
          },
          {
            "internalType": "uint256",
            "name": "lastAdjustmentTime",
            "type": "uint256"
          }
        ],
        "internalType": "struct ThreeGatesRiskManager.UserRiskProfile",
        "name": "profile",
        "type": "tuple"
      }
    ],
    "stateMutability": "view",
    "type": "function"
  },
  {
    "inputs": [
      {
        "internalType": "address",
        "name": "user",
        "type": "address"
      }
    ],
    "name": "getUserUtilization",
    "outputs": [
      {
        "internalType": "uint256",
        "name": "singleWindow",
        "type": "uint256"
      },
      {
        "internalType": "uint256",
        "name": "fifteenMinute",
        "type": "uint256"
      },
      {
        "internalType": "uint256",
        "name": "twentyFourHour",
        "type": "uint256"
      }
    ],
    "stateMutability": "view",
    "type": "function"
  },
  {
    "inputs": [],
    "name": "getViolationStats",
    "outputs": [
      {
        "internalType": "uint256",
        "name": "total",
        "type": "uint256"
      },
      {
        "internalType": "uint256",
        "name": "singleWindow",
        "type": "uint256"
      },
      {
        "internalType": "uint256",
        "name": "fifteenMinute",
        "type": "uint256"
      },
      {
        "internalType": "uint256",
        "name": "twentyFourHour",
        "type": "uint256"
      }
    ],
    "stateMutability": "view",
    "type": "function"
  },
  {
    "inputs": [],
    "name": "globalRiskScore",
    "outputs": [
      {
        "internalType": "uint256",
        "name": "",
        "type": "uint256"
      }
    ],
    "stateMutability": "view",
    "type": "function"
  },
  {
    "inputs": [
      {
        "internalType": "bytes32",
        "name": "role",
        "type": "bytes32"
      },
      {
        "internalType": "address",
        "name": "account",
        "type": "address"
      }
    ],
    "name": "grantRole",
    "outputs": [],
    "stateMutability": "nonpayable",
    "type": "function"
  },
  {
    "inputs": [
      {
        "internalType": "bytes32",
        "name": "role",
        "type": "bytes32"
      },
      {
        "internalType": "address",
        "name": "account",
        "type": "address"
      }
    ],
    "name": "hasRole",
    "outputs": [
      {
        "internalType": "bool",
        "name": "",
        "type": "bool"
      }
    ],
    "stateMutability": "view",
    "type": "function"
  },
  {
    "inputs": [
      {
        "internalType": "address",
        "name": "_admin",
        "type": "address"
      }
    ],
    "name": "initialize",
    "outputs": [],
    "stateMutability": "nonpayable",
    "type": "function"
  },
  {
    "inputs": [],
    "name": "lastGlobalAdjustment",
    "outputs": [
      {
        "internalType": "uint256",
        "name": "",
        "type": "uint256"
      }
    ],
    "stateMutability": "view",
    "type": "function"
  },
  {
    "inputs": [],
    "name": "liquidityAdjustmentFactor",
    "outputs": [
      {
        "internalType": "uint256",
        "name": "",
        "type": "uint256"
      }
    ],
    "stateMutability": "view",
    "type": "function"
  },
  {
    "inputs": [
      {
        "internalType": "bytes32",
        "name": "",
        "type": "bytes32"
      },
      {
        "internalType": "enum ThreeGatesRiskManager.GateType",
        "name": "",
        "type": "uint8"
      }
    ],
    "name": "marketCircuitBreakers",
    "outputs": [
      {
        "internalType": "uint256",
        "name": "threshold",
        "type": "uint256"
      },
      {
        "internalType": "uint256",
        "name": "duration",
        "type": "uint256"
      },
      {
        "internalType": "uint256",
        "name": "cooldownPeriod",
        "type": "uint256"
      },
      {
        "internalType": "uint256",
        "name": "lastTriggered",
        "type": "uint256"
      },
      {
        "internalType": "bool",
        "name": "isTriggered",
        "type": "bool"
      },
      {
        "internalType": "bool",
        "name": "isActive",
        "type": "bool"
      },
      {
        "internalType": "uint256",
        "name": "triggerCount",
        "type": "uint256"
      }
    ],
    "stateMutability": "view",
    "type": "function"
  },
  {
    "inputs": [
      {
        "internalType": "bytes32",
        "name": "",
        "type": "bytes32"
      }
    ],
    "name": "marketConfigs",
    "outputs": [
      {
        "components": [
          {
            "internalType": "uint256",
            "name": "limit",
            "type": "uint256"
          },
          {
            "internalType": "uint256",
            "name": "currentUsage",
            "type": "uint256"
          },
          {
            "internalType": "uint256",
            "name": "lastResetTime",
            "type": "uint256"
          },
          {
            "internalType": "uint256",
            "name": "resetInterval",
            "type": "uint256"
          },
          {
            "internalType": "bool",
            "name": "isActive",
            "type": "bool"
          },
          {
            "internalType": "uint256",
            "name": "utilizationRate",
            "type": "uint256"
          }
        ],
        "internalType": "struct ThreeGatesRiskManager.RiskGate",
        "name": "singleWindow",
        "type": "tuple"
      },
      {
        "components": [
          {
            "internalType": "uint256",
            "name": "limit",
            "type": "uint256"
          },
          {
            "internalType": "uint256",
            "name": "currentUsage",
            "type": "uint256"
          },
          {
            "internalType": "uint256",
            "name": "lastResetTime",
            "type": "uint256"
          },
          {
            "internalType": "uint256",
            "name": "resetInterval",
            "type": "uint256"
          },
          {
            "internalType": "bool",
            "name": "isActive",
            "type": "bool"
          },
          {
            "internalType": "uint256",
            "name": "utilizationRate",
            "type": "uint256"
          }
        ],
        "internalType": "struct ThreeGatesRiskManager.RiskGate",
        "name": "fifteenMinute",
        "type": "tuple"
      },
      {
        "components": [
          {
            "internalType": "uint256",
            "name": "limit",
            "type": "uint256"
          },
          {
            "internalType": "uint256",
            "name": "currentUsage",
            "type": "uint256"
          },
          {
            "internalType": "uint256",
            "name": "lastResetTime",
            "type": "uint256"
          },
          {
            "internalType": "uint256",
            "name": "resetInterval",
            "type": "uint256"
          },
          {
            "internalType": "bool",
            "name": "isActive",
            "type": "bool"
          },
          {
            "internalType": "uint256",
            "name": "utilizationRate",
            "type": "uint256"
          }
        ],
        "internalType": "struct ThreeGatesRiskManager.RiskGate",
        "name": "twentyFourHour",
        "type": "tuple"
      },
      {
        "internalType": "uint256",
        "name": "volatilityScore",
        "type": "uint256"
      },
      {
        "internalType": "uint256",
        "name": "liquidityScore",
        "type": "uint256"
      },
      {
        "internalType": "uint256",
        "name": "openInterest",
        "type": "uint256"
      },
      {
        "internalType": "uint256",
        "name": "dailyVolume",
        "type": "uint256"
      },
      {
        "internalType": "uint256",
        "name": "maxLeverage",
        "type": "uint256"
      },
      {
        "internalType": "uint256",
        "name": "marginRequirement",
        "type": "uint256"
      },
      {
        "internalType": "uint256",
        "name": "liquidationBuffer",
        "type": "uint256"
      },
      {
        "internalType": "bool",
        "name": "isActive",
        "type": "bool"
      },
      {
        "internalType": "bool",
        "name": "emergencyMode",
        "type": "bool"
      }
    ],
    "stateMutability": "view",
    "type": "function"
  },
  {
    "inputs": [
      {
        "internalType": "bytes32",
        "name": "",
        "type": "bytes32"
      }
    ],
    "name": "marketExists",
    "outputs": [
      {
        "internalType": "bool",
        "name": "",
        "type": "bool"
      }
    ],
    "stateMutability": "view",
    "type": "function"
  },
  {
    "inputs": [
      {
        "internalType": "bytes32",
        "name": "",
        "type": "bytes32"
      }
    ],
    "name": "marketViolations",
    "outputs": [
      {
        "internalType": "uint256",
        "name": "",
        "type": "uint256"
      }
    ],
    "stateMutability": "view",
    "type": "function"
  },
  {
    "inputs": [
      {
        "internalType": "bytes32",
        "name": "role",
        "type": "bytes32"
      },
      {
        "internalType": "address",
        "name": "callerConfirmation",
        "type": "address"
      }
    ],
    "name": "renounceRole",
    "outputs": [],
    "stateMutability": "nonpayable",
    "type": "function"
  },
  {
    "inputs": [
      {
        "internalType": "enum ThreeGatesRiskManager.GateType",
        "name": "gateType",
        "type": "uint8"
      },
      {
        "internalType": "address",
        "name": "user",
        "type": "address"
      },
      {
        "internalType": "bytes32",
        "name": "market",
        "type": "bytes32"
      }
    ],
    "name": "resetCircuitBreaker",
    "outputs": [],
    "stateMutability": "nonpayable",
    "type": "function"
  },
  {
    "inputs": [
      {
        "internalType": "bytes32",
        "name": "role",
        "type": "bytes32"
      },
      {
        "internalType": "address",
        "name": "account",
        "type": "address"
      }
    ],
    "name": "revokeRole",
    "outputs": [],
    "stateMutability": "nonpayable",
    "type": "function"
  },
  {
    "inputs": [
      {
        "internalType": "bytes32",
        "name": "",
        "type": "bytes32"
      }
    ],
    "name": "riskEvents",
    "outputs": [
      {
        "internalType": "bytes32",
        "name": "eventId",
        "type": "bytes32"
      },
      {
        "internalType": "address",
        "name": "user",
        "type": "address"
      },
      {
        "internalType": "bytes32",
        "name": "market",
        "type": "bytes32"
      },
      {
        "internalType": "enum ThreeGatesRiskManager.GateType",
        "name": "gateType",
        "type": "uint8"
      },
      {
        "internalType": "uint256",
        "name": "attemptedAmount",
        "type": "uint256"
      },
      {
        "internalType": "uint256",
        "name": "currentLimit",
        "type": "uint256"
      },
      {
        "internalType": "uint256",
        "name": "timestamp",
        "type": "uint256"
      },
      {
        "internalType": "bool",
        "name": "isViolation",
        "type": "bool"
      },
      {
        "internalType": "string",
        "name": "description",
        "type": "string"
      }
    ],
    "stateMutability": "view",
    "type": "function"
  },
  {
    "inputs": [
      {
        "internalType": "bool",
        "name": "enabled",
        "type": "bool"
      },
      {
        "internalType": "string",
        "name": "reason",
        "type": "string"
      }
    ],
    "name": "setSystemEmergencyMode",
    "outputs": [],
    "stateMutability": "nonpayable",
    "type": "function"
  },
  {
    "inputs": [
      {
        "internalType": "bytes4",
        "name": "interfaceId",
        "type": "bytes4"
      }
    ],
    "name": "supportsInterface",
    "outputs": [
      {
        "internalType": "bool",
        "name": "",
        "type": "bool"
      }
    ],
    "stateMutability": "view",
    "type": "function"
  },
  {
    "inputs": [],
    "name": "systemEmergencyMode",
    "outputs": [
      {
        "internalType": "bool",
        "name": "",
        "type": "bool"
      }
    ],
    "stateMutability": "view",
    "type": "function"
  },
  {
    "inputs": [],
    "name": "systemLeverageRatio",
    "outputs": [
      {
        "internalType": "uint256",
        "name": "",
        "type": "uint256"
      }
    ],
    "stateMutability": "view",
    "type": "function"
  },
  {
    "inputs": [],
    "name": "totalGateChecks",
    "outputs": [
      {
        "internalType": "uint256",
        "name": "",
        "type": "uint256"
      }
    ],
    "stateMutability": "view",
    "type": "function"
  },
  {
    "inputs": [],
    "name": "totalRiskEvents",
    "outputs": [
      {
        "internalType": "uint256",
        "name": "",
        "type": "uint256"
      }
    ],
    "stateMutability": "view",
    "type": "function"
  },
  {
    "inputs": [],
    "name": "totalSystemExposure",
    "outputs": [
      {
        "internalType": "uint256",
        "name": "",
        "type": "uint256"
      }
    ],
    "stateMutability": "view",
    "type": "function"
  },
  {
    "inputs": [],
    "name": "totalViolations",
    "outputs": [
      {
        "internalType": "uint256",
        "name": "",
        "type": "uint256"
      }
    ],
    "stateMutability": "view",
    "type": "function"
  },
  {
    "inputs": [
      {
        "internalType": "address",
        "name": "user",
        "type": "address"
      },
      {
        "internalType": "enum ThreeGatesRiskManager.GateType",
        "name": "gateType",
        "type": "uint8"
      },
      {
        "internalType": "uint256",
        "name": "newLimit",
        "type": "uint256"
      }
    ],
    "name": "updateUserRiskLimit",
    "outputs": [],
    "stateMutability": "nonpayable",
    "type": "function"
  },
  {
    "inputs": [
      {
        "internalType": "address",
        "name": "",
        "type": "address"
      },
      {
        "internalType": "enum ThreeGatesRiskManager.GateType",
        "name": "",
        "type": "uint8"
      }
    ],
    "name": "userCircuitBreakers",
    "outputs": [
      {
        "internalType": "uint256",
        "name": "threshold",
        "type": "uint256"
      },
      {
        "internalType": "uint256",
        "name": "duration",
        "type": "uint256"
      },
      {
        "internalType": "uint256",
        "name": "cooldownPeriod",
        "type": "uint256"
      },
      {
        "internalType": "uint256",
        "name": "lastTriggered",
        "type": "uint256"
      },
      {
        "internalType": "bool",
        "name": "isTriggered",
        "type": "bool"
      },
      {
        "internalType": "bool",
        "name": "isActive",
        "type": "bool"
      },
      {
        "internalType": "uint256",
        "name": "triggerCount",
        "type": "uint256"
      }
    ],
    "stateMutability": "view",
    "type": "function"
  },
  {
    "inputs": [
      {
        "internalType": "address",
        "name": "",
        "type": "address"
      }
    ],
    "name": "userExists",
    "outputs": [
      {
        "internalType": "bool",
        "name": "",
        "type": "bool"
      }
    ],
    "stateMutability": "view",
    "type": "function"
  },
  {
    "inputs": [
      {
        "internalType": "address",
        "name": "",
        "type": "address"
      }
    ],
    "name": "userProfiles",
    "outputs": [
      {
        "components": [
          {
            "internalType": "uint256",
            "name": "limit",
            "type": "uint256"
          },
          {
            "internalType": "uint256",
            "name": "currentUsage",
            "type": "uint256"
          },
          {
            "internalType": "uint256",
            "name": "lastResetTime",
            "type": "uint256"
          },
          {
            "internalType": "uint256",
            "name": "resetInterval",
            "type": "uint256"
          },
          {
            "internalType": "bool",
            "name": "isActive",
            "type": "bool"
          },
          {
            "internalType": "uint256",
            "name": "utilizationRate",
            "type": "uint256"
          }
        ],
        "internalType": "struct ThreeGatesRiskManager.RiskGate",
        "name": "singleWindow",
        "type": "tuple"
      },
      {
        "components": [
          {
            "internalType": "uint256",
            "name": "limit",
            "type": "uint256"
          },
          {
            "internalType": "uint256",
            "name": "currentUsage",
            "type": "uint256"
          },
          {
            "internalType": "uint256",
            "name": "lastResetTime",
            "type": "uint256"
          },
          {
            "internalType": "uint256",
            "name": "resetInterval",
            "type": "uint256"
          },
          {
            "internalType": "bool",
            "name": "isActive",
            "type": "bool"
          },
          {
            "internalType": "uint256",
            "name": "utilizationRate",
            "type": "uint256"
          }
        ],
        "internalType": "struct ThreeGatesRiskManager.RiskGate",
        "name": "fifteenMinute",
        "type": "tuple"
      },
      {
        "components": [
          {
            "internalType": "uint256",
            "name": "limit",
            "type": "uint256"
          },
          {
            "internalType": "uint256",
            "name": "currentUsage",
            "type": "uint256"
          },
          {
            "internalType": "uint256",
            "name": "lastResetTime",
            "type": "uint256"
          },
          {
            "internalType": "uint256",
            "name": "resetInterval",
            "type": "uint256"
          },
          {
            "internalType": "bool",
            "name": "isActive",
            "type": "bool"
          },
          {
            "internalType": "uint256",
            "name": "utilizationRate",
            "type": "uint256"
          }
        ],
        "internalType": "struct ThreeGatesRiskManager.RiskGate",
        "name": "twentyFourHour",
        "type": "tuple"
      },
      {
        "internalType": "uint256",
        "name": "riskScore",
        "type": "uint256"
      },
      {
        "internalType": "enum ThreeGatesRiskManager.RiskLevel",
        "name": "riskLevel",
        "type": "uint8"
      },
      {
        "internalType": "uint256",
        "name": "totalExposure",
        "type": "uint256"
      },
      {
        "internalType": "uint256",
        "name": "leverageRatio",
        "type": "uint256"
      },
      {
        "internalType": "uint256",
        "name": "violationCount",
        "type": "uint256"
      },
      {
        "internalType": "uint256",
        "name": "lastViolationTime",
        "type": "uint256"
      },
      {
        "internalType": "uint256",
        "name": "averageTradeSize",
        "type": "uint256"
      },
      {
        "internalType": "uint256",
        "name": "tradingFrequency",
        "type": "uint256"
      },
      {
        "internalType": "bool",
        "name": "dynamicLimitsEnabled",
        "type": "bool"
      },
      {
        "internalType": "uint256",
        "name": "adjustmentFactor",
        "type": "uint256"
      },
      {
        "internalType": "uint256",
        "name": "lastAdjustmentTime",
        "type": "uint256"
      }
    ],
    "stateMutability": "view",
    "type": "function"
  },
  {
    "inputs": [
      {
        "internalType": "address",
        "name": "",
        "type": "address"
      }
    ],
    "name": "userViolations",
    "outputs": [
      {
        "internalType": "uint256",
        "name": "",
        "type": "uint256"
      }
    ],
    "stateMutability": "view",
    "type": "function"
  },
  {
    "inputs": [],
    "name": "volatilityAdjustmentFactor",
    "outputs": [
      {
        "internalType": "uint256",
        "name": "",
        "type": "uint256"
      }
    ],
    "stateMutability": "view",
    "type": "function"
  }
]